[
  {
    "$type": "ModListMetadata, Wabbajack.Lib",
    "title": "Tuxborn",
    "description": "Tuxborn is a performance & content-focused Wabbajack modlist, with profiles tailored for both handheld devices and laptops/desktop PCs. Using a combination of mods from Enairim and Simonrim with optional modern combat based on BFCO.",
    "author": "Omni and Ouroboros",
    "maintainers": [
      "github/Ouruboros"
    ],
    "game": "skyrimspecialedition",
    "tags": [
      "DLC Required",
      "SFW",
      "Steam Deck",
      "Steam"
    ],
    "nsfw": false,
    "image_contains_title": true,
    "force_down": false,
    "links": {
      "$type": "Links, Wabbajack.Lib",
      "image": "https://raw.githubusercontent.com/Omni-guides/Tuxborn/main/images/Splash.png",
      "readme": "https://github.com/Omni-guides/Tuxborn/blob/main/README.md",
      "download": "https://authored-files.wabbajack.org/Tuxborn.wabbajack_b96e8113-3dd1-4257-afcd-5a7cb984fb6b",
      "machineURL": "Tuxborn",
      "discordURL": "https://discord.com/invite/xRrHRsb5e9"
    },
    "download_metadata": {
      "$type": "DownloadMetadata, Wabbajack.Lib",
      "Hash": "HfNfLXqrCz4",
      "Size": 2885126721,
      "NumberOfArchives": 1791,
      "SizeOfArchives": 147453912353,
      "NumberOfInstalledFiles": 381247,
      "SizeOfInstalledFiles": 218926457577,
      "TotalSize":366380369930
    },
    "version": "1.1.1"
  }
]

